[
  {
    "id": "SP-B-01",
    "language": "Spanish",
    "level": "Beginner",
    "phase": 1,
    "title": "Spanish for Beginners: Greetings & Introductions",
    "url": "https://www.youtube.com/watch?v=hyLl_0d0EBw",
    "channel": "SpanishPod101",
    "focus_areas": "Greetings, basic introductions, and key vocabulary."
  },
  {
    "id": "SP-B-02",
    "language": "Spanish",
    "level": "Beginner",
    "phase": 1,
    "title": "Spanish Alphabet & Pronunciation Guide",
    "url": "https://www.youtube.com/watch?v=kJQjXAVEWt0",
    "channel": "Butterfly Spanish",
    "focus_areas": "Mastering the sounds of Spanish vowels and consonants."
  },
  {
    "id": "SP-B-03",
    "language": "Spanish",
    "level": "Beginner",
    "phase": 1,
    "title": "100 Most Common Spanish Words & Phrases",
    "url": "https://www.youtube.com/watch?v=6_5FnCLLYoA",
    "channel": "SpanishDict",
    "focus_areas": "The core vocabulary necessary for day-to-day conversation."
  },
  {
    "id": "SP-B-04",
    "language": "Spanish",
    "level": "Beginner",
    "phase": 1,
    "title": "How to Use 'Ser' vs 'Estar' Natively",
    "url": "https://www.youtube.com/watch?v=bmpPhSNt1J4",
    "channel": "The Language Tutor",
    "focus_areas": "Demystifying the two essential Spanish 'to be' verbs."
  },
  {
    "id": "SP-B-05",
    "language": "Spanish",
    "level": "Beginner",
    "phase": 1,
    "title": "Spanish Numbers 1-100 Made Simple",
    "url": "https://www.youtube.com/watch?v=qIyhRvk7qlk",
    "channel": "SpanishPod101",
    "focus_areas": "Counting and pronouncing numbers in Spanish context."
  },
  {
    "id": "SP-B-06",
    "language": "Spanish",
    "level": "Beginner",
    "phase": 1,
    "title": "Subject Pronouns in Spanish Explained",
    "url": "https://www.youtube.com/watch?v=R2xL7C1jnxM",
    "channel": "Butterfly Spanish",
    "focus_areas": "Yo, Tú, Él, Ella, Nosotros, and more."
  },
  {
    "id": "SP-B-07",
    "language": "Spanish",
    "level": "Beginner",
    "phase": 1,
    "title": "Present Tense Regular -AR Verbs",
    "url": "https://www.youtube.com/watch?v=TF71Ca3def8",
    "channel": "Spanishland School",
    "focus_areas": "Conjugating basic present tense verbs."
  },
  {
    "id": "SP-B-08",
    "language": "Spanish",
    "level": "Beginner",
    "phase": 1,
    "title": "Present Tense Regular -ER & -IR Verbs",
    "url": "https://www.youtube.com/watch?v=P1i5BrPAELU",
    "channel": "The Language Tutor",
    "focus_areas": "Mastering the remaining basic regular verb groups."
  },
  {
    "id": "SP-B-09",
    "language": "Spanish",
    "level": "Beginner",
    "phase": 1,
    "title": "Definite vs Indefinite Articles (El, La, Un, Una)",
    "url": "https://www.youtube.com/watch?v=Zs5YzrX7a8g",
    "channel": "SpanishDict",
    "focus_areas": "Nouns, gender alignment, and articles."
  },
  {
    "id": "SP-B-10",
    "language": "Spanish",
    "level": "Beginner",
    "phase": 1,
    "title": "Plural Nouns and Adjective Agreement",
    "url": "https://www.youtube.com/watch?v=2B_TK_aun8E",
    "channel": "Butterfly Spanish",
    "focus_areas": "Making nouns and describing adjectives agree in gender and number."
  },
  {
    "id": "SP-B-11",
    "language": "Spanish",
    "level": "Beginner",
    "phase": 2,
    "title": "Daily Routine & Reflexive Verbs in Spanish",
    "url": "https://www.youtube.com/watch?v=5-_Aog7Jsjk",
    "channel": "Dreaming Spanish",
    "focus_areas": "How to talk about waking up, working, and daily habits."
  },
  {
    "id": "SP-B-12",
    "language": "Spanish",
    "level": "Beginner",
    "phase": 2,
    "title": "Asking for Directions in Spanish (Travel Essential)",
    "url": "https://www.youtube.com/watch?v=qedMBso9k76",
    "channel": "Spanish and Go",
    "focus_areas": "Key travel phrases for navigating Spanish-speaking cities."
  },
  {
    "id": "SP-B-13",
    "language": "Spanish",
    "level": "Beginner",
    "phase": 2,
    "title": "How to Order Food in Spanish Restaurants",
    "url": "https://www.youtube.com/watch?v=_raLMEnUGbI",
    "channel": "Spanish and Go",
    "focus_areas": "Ordering plates, asking for the check, and food vocab."
  },
  {
    "id": "SP-B-14",
    "language": "Spanish",
    "level": "Beginner",
    "phase": 2,
    "title": "Telling Time and Planning Schedules in Spanish",
    "url": "https://www.youtube.com/watch?v=yKU5XZtweXM",
    "channel": "The Language Tutor",
    "focus_areas": "Hours, minutes, and scheduling days."
  },
  {
    "id": "SP-B-15",
    "language": "Spanish",
    "level": "Beginner",
    "phase": 2,
    "title": "Spanish Family Vocabulary & Possessive Adjectives",
    "url": "https://www.youtube.com/watch?v=4q80FN8_5x0",
    "channel": "SpanishPod101",
    "focus_areas": "Describing your family members and showing ownership."
  },
  {
    "id": "SP-B-16",
    "language": "Spanish",
    "level": "Beginner",
    "phase": 2,
    "title": "Weather Expressions & Calendar Terms",
    "url": "https://www.youtube.com/watch?v=rUJb7CcoTOV",
    "channel": "Butterfly Spanish",
    "focus_areas": "Talking about weather, seasons, months, and days."
  },
  {
    "id": "SP-B-17",
    "language": "Spanish",
    "level": "Beginner",
    "phase": 2,
    "title": "Essential Gym & Fitness Spanish Vocabulary",
    "url": "https://www.youtube.com/watch?v=b-KIdLNn_O0",
    "channel": "Speak Spanish Faster",
    "focus_areas": "Fitness vocabulary including anatomy, muscle names, and gym gear."
  },
  {
    "id": "SP-B-18",
    "language": "Spanish",
    "level": "Beginner",
    "phase": 2,
    "title": "Shopping and Grocery Vocabulary in Spanish",
    "url": "https://www.youtube.com/watch?v=41S4SiUuIxY",
    "channel": "Spanish and Go",
    "focus_areas": "Words for food items, market shopping, and checkout."
  },
  {
    "id": "SP-B-19",
    "language": "Spanish",
    "level": "Beginner",
    "phase": 2,
    "title": "Basic Conversational Connectors (Y, Pero, Porque, Entonces)",
    "url": "https://www.youtube.com/watch?v=VETQDyErJ_6",
    "channel": "Dreaming Spanish",
    "focus_areas": "Linking your sentences to sound more natural."
  },
  {
    "id": "SP-B-20",
    "language": "Spanish",
    "level": "Beginner",
    "phase": 2,
    "title": "Simple Future Tense with 'Ir + A + Infinitive'",
    "url": "https://www.youtube.com/watch?v=Oyckweo6P39",
    "channel": "The Language Tutor",
    "focus_areas": "Talking about what you are going to do next."
  },
  {
    "id": "SP-I-01",
    "language": "Spanish",
    "level": "Intermediate",
    "phase": 3,
    "title": "Preterite Tense Regular Verbs (Past Tense)",
    "url": "https://www.youtube.com/watch?v=dlDn2ah1y0g",
    "channel": "Butterfly Spanish",
    "focus_areas": "Mastering the basic past tense for completed actions."
  },
  {
    "id": "SP-I-02",
    "language": "Spanish",
    "level": "Intermediate",
    "phase": 3,
    "title": "Imperfect Tense Regular Verbs (Past Tense)",
    "url": "https://www.youtube.com/watch?v=AmnTX30VliE",
    "channel": "The Language Tutor",
    "focus_areas": "Describing ongoing or habitual actions in the past."
  },
  {
    "id": "SP-I-03",
    "language": "Spanish",
    "level": "Intermediate",
    "phase": 3,
    "title": "Preterite vs Imperfect: The Ultimate Battle",
    "url": "https://www.youtube.com/watch?v=LvhO2-azzig",
    "channel": "Spanishland School",
    "focus_areas": "Knowing which past tense to use in real-world conversations."
  },
  {
    "id": "SP-I-04",
    "language": "Spanish",
    "level": "Intermediate",
    "phase": 3,
    "title": "Direct and Indirect Object Pronouns Together",
    "url": "https://www.youtube.com/watch?v=bRncX-pkwD0",
    "channel": "Butterfly Spanish",
    "focus_areas": "Using 'lo', 'la', 'le', and 'se' efficiently."
  },
  {
    "id": "SP-I-05",
    "language": "Spanish",
    "level": "Intermediate",
    "phase": 3,
    "title": "Subjunctive Mood Basics: Expressing Wishes & Hopes",
    "url": "https://www.youtube.com/watch?v=CRvXpo45oHw",
    "channel": "Español con Juan",
    "focus_areas": "Introduction to the Spanish subjunctive structure."
  },
  {
    "id": "SP-I-06",
    "language": "Spanish",
    "level": "Intermediate",
    "phase": 3,
    "title": "Subjunctive vs Indicative: Key Triggers Explained",
    "url": "https://www.youtube.com/watch?v=vUfJswOD-I8",
    "channel": "Spanishland School",
    "focus_areas": "When to switch to subjunctive in conversation."
  },
  {
    "id": "SP-I-07",
    "language": "Spanish",
    "level": "Intermediate",
    "phase": 3,
    "title": "How to Use 'Por' and 'Para' Correctly",
    "url": "https://www.youtube.com/watch?v=02Am4LlPGjU",
    "channel": "The Language Tutor",
    "focus_areas": "Simplifying the rules for these two complex prepositions."
  },
  {
    "id": "SP-I-08",
    "language": "Spanish",
    "level": "Intermediate",
    "phase": 3,
    "title": "Conversational Spanish Connectors for Flow",
    "url": "https://www.youtube.com/watch?v=O9A7S9Jfkfk",
    "channel": "Español con Juan",
    "focus_areas": "Using transition words to sound like a native speaker."
  },
  {
    "id": "SP-I-09",
    "language": "Spanish",
    "level": "Intermediate",
    "phase": 3,
    "title": "Conditional Tense: 'I Would Do It'",
    "url": "https://www.youtube.com/watch?v=nRaMf1Y1TCM",
    "channel": "Butterfly Spanish",
    "focus_areas": "Forming and using hypothetical conditional statements."
  },
  {
    "id": "SP-I-10",
    "language": "Spanish",
    "level": "Intermediate",
    "phase": 3,
    "title": "Future Simple Tense: Regular & Irregular",
    "url": "https://www.youtube.com/watch?v=U42loE1zhdw",
    "channel": "The Language Tutor",
    "focus_areas": "Conjugating the true future tense for plans and predictions."
  },
  {
    "id": "SP-I-11",
    "language": "Spanish",
    "level": "Intermediate",
    "phase": 3,
    "title": "Spanish Idioms and Slang (Latin America)",
    "url": "https://www.youtube.com/watch?v=R9A7S9Jfkfk",
    "channel": "Spanish and Go",
    "focus_areas": "High-leverage colloquial phrases for everyday travel."
  },
  {
    "id": "SP-I-12",
    "language": "Spanish",
    "level": "Intermediate",
    "phase": 3,
    "title": "Reflexive Verbs: Advanced Uses and Nuances",
    "url": "https://www.youtube.com/watch?v=S9A7S9Jfkfk",
    "channel": "Dreaming Spanish",
    "focus_areas": "Verbs that change meaning when used reflexively."
  },
  {
    "id": "SP-I-13",
    "language": "Spanish",
    "level": "Intermediate",
    "phase": 3,
    "title": "Health, Sickness, and Medical Spanish",
    "url": "https://www.youtube.com/watch?v=nmiTCjf2-SQ",
    "channel": "The Language Tutor",
    "focus_areas": "Vocabulary for describing symptoms, body parts, and clinical terms."
  },
  {
    "id": "SP-I-14",
    "language": "Spanish",
    "level": "Intermediate",
    "phase": 3,
    "title": "Imperative Mood: Giving Commands in the Gym",
    "url": "https://www.youtube.com/watch?v=C2UnO5khpi4",
    "channel": "Spanishland School",
    "focus_areas": "How to give clear cues, directions, and commands natively."
  },
  {
    "id": "SP-I-15",
    "language": "Spanish",
    "level": "Intermediate",
    "phase": 3,
    "title": "Passive 'Se' and Impersonal 'Se'",
    "url": "https://www.youtube.com/watch?v=V9A7S9Jfkfk",
    "channel": "Butterfly Spanish",
    "focus_areas": "Constructing general statements using 'se vende' or 'se dice'."
  },
  {
    "id": "SP-A-01",
    "language": "Spanish",
    "level": "Advanced",
    "phase": 4,
    "title": "Past Subjunctive (Imperfect Subjunctive) Guide",
    "url": "https://www.youtube.com/watch?v=5VkCYZGvNlI",
    "channel": "Spanishland School",
    "focus_areas": "Forming 'Si yo fuera...' and expressing past doubts."
  },
  {
    "id": "SP-A-02",
    "language": "Spanish",
    "level": "Advanced",
    "phase": 4,
    "title": "Compound Subjunctive: Present & Pluperfect",
    "url": "https://www.youtube.com/watch?v=am0YiYkTQ_E",
    "channel": "María Español",
    "focus_areas": "Advanced subjunctive structures for complex thoughts."
  },
  {
    "id": "SP-A-03",
    "language": "Spanish",
    "level": "Advanced",
    "phase": 4,
    "title": "Hypothetical If-Clauses in Spanish",
    "url": "https://www.youtube.com/watch?v=Y9A7S9Jfkfk",
    "channel": "Butterfly Spanish",
    "focus_areas": "Combining past subjunctive with conditional tenses."
  },
  {
    "id": "SP-A-04",
    "language": "Spanish",
    "level": "Advanced",
    "phase": 4,
    "title": "Advanced Discourse Markers for Debate",
    "url": "https://www.youtube.com/watch?v=Z9A7S9Jfkfk",
    "channel": "Español con Juan",
    "focus_areas": "Transition phrases for expressing complex arguments."
  },
  {
    "id": "SP-A-05",
    "language": "Spanish",
    "level": "Advanced",
    "phase": 4,
    "title": "Understanding Native Accents: Spain vs Caribbean vs Mexico",
    "url": "https://www.youtube.com/watch?v=a9A7S9Jfkfk",
    "channel": "Spanish and Go",
    "focus_areas": "Developing listening comprehension for fast spoken dialects."
  },
  {
    "id": "SP-A-06",
    "language": "Spanish",
    "level": "Advanced",
    "phase": 4,
    "title": "Advanced Relative Pronouns: Que, Quien, Cuyo",
    "url": "https://www.youtube.com/watch?v=b9A7S9Jfkfk",
    "channel": "The Language Tutor",
    "focus_areas": "Connecting descriptive clauses using advanced syntax."
  },
  {
    "id": "SP-A-07",
    "language": "Spanish",
    "level": "Advanced",
    "phase": 4,
    "title": "The Neutral 'Lo' and its Many Uses",
    "url": "https://www.youtube.com/watch?v=c9A7S9Jfkfk",
    "channel": "Butterfly Spanish",
    "focus_areas": "Mastering 'lo bueno', 'lo que', and other abstract expressions."
  },
  {
    "id": "SP-A-08",
    "language": "Spanish",
    "level": "Advanced",
    "phase": 4,
    "title": "Advanced Coaching Cues & Manifestation in Spanish",
    "url": "https://www.youtube.com/watch?v=d9A7S9Jfkfk",
    "channel": "Speak Spanish Faster",
    "focus_areas": "Detailed scripts for athletic mindset training and coaching cues."
  },
  {
    "id": "SP-A-09",
    "language": "Spanish",
    "level": "Advanced",
    "phase": 4,
    "title": "Gerund vs Infinitive: Advanced Syntactical Differences",
    "url": "https://www.youtube.com/watch?v=e9A7S9Jfkfk",
    "channel": "María Español",
    "focus_areas": "Knowing when to use present participle vs base verb."
  },
  {
    "id": "SP-A-10",
    "language": "Spanish",
    "level": "Advanced",
    "phase": 4,
    "title": "Subtle Verb Nuances: Acabar, Volver, Volverse",
    "url": "https://www.youtube.com/watch?v=f9A7S9Jfkfk",
    "channel": "Español con Juan",
    "focus_areas": "Idiomatic verbs that describe actions, returns, and transformations."
  },
  {
    "id": "SP-A-11",
    "language": "Spanish",
    "level": "Advanced",
    "phase": 4,
    "title": "Caribbean Spanish Slang and Pronunciation (Medellín/Caribbean)",
    "url": "https://www.youtube.com/watch?v=g9A7S9Jfkfk",
    "channel": "Why Not Spanish?",
    "focus_areas": "Navigating slang and speed in Colombia and the Caribbean."
  },
  {
    "id": "SP-A-12",
    "language": "Spanish",
    "level": "Advanced",
    "phase": 4,
    "title": "Advanced Medical Anatomy & Physiology in Spanish",
    "url": "https://www.youtube.com/watch?v=h9A7S9Jfkfk",
    "channel": "The Language Tutor",
    "focus_areas": "Technical terminology for medical and exercise science fields."
  },
  {
    "id": "SP-A-13",
    "language": "Spanish",
    "level": "Advanced",
    "phase": 4,
    "title": "Narrating Stories in the Past: Mastering 3 Past Tenses",
    "url": "https://www.youtube.com/watch?v=i9A7S9Jfkfk",
    "channel": "Dreaming Spanish",
    "focus_areas": "Weaving preterite, imperfect, and pluperfect into rich narratives."
  },
  {
    "id": "SP-A-14",
    "language": "Spanish",
    "level": "Advanced",
    "phase": 4,
    "title": "Expressing Double Negatives & Nuanced Expressions",
    "url": "https://www.youtube.com/watch?v=j9A7S9Jfkfk",
    "channel": "Butterfly Spanish",
    "focus_areas": "Using negative words correctly according to Spanish grammar rules."
  },
  {
    "id": "SP-A-15",
    "language": "Spanish",
    "level": "Advanced",
    "phase": 4,
    "title": "Advanced Speed Reading & Accent Marks (Tildes)",
    "url": "https://www.youtube.com/watch?v=k9A7S9Jfkfk",
    "channel": "María Español",
    "focus_areas": "Perfecting written grammar, stress rules, and written accents."
  },
  {
    "id": "PO-B-01",
    "language": "Portuguese",
    "level": "Beginner",
    "phase": 1,
    "title": "Learn Portuguese in 50 Minutes - ALL Basics You Need",
    "url": "https://www.youtube.com/watch?v=4VxHVpMaK_0",
    "channel": "PortuguesePod101",
    "focus_areas": "The perfect baseline introduction to Portuguese basics."
  },
  {
    "id": "PO-B-02",
    "language": "Portuguese",
    "level": "Beginner",
    "phase": 1,
    "title": "Brazilian Portuguese Pronunciation Hacks",
    "url": "https://www.youtube.com/watch?v=5NtlrYbp5UI",
    "channel": "Speaking Brazilian",
    "focus_areas": "Mastering nasal vowels and tricky consonant sounds."
  },
  {
    "id": "PO-B-03",
    "language": "Portuguese",
    "level": "Beginner",
    "phase": 1,
    "title": "Greetings and Essential Social Phrases in Brazil",
    "url": "https://www.youtube.com/watch?v=eDXojcGgsCU",
    "channel": "Hello Rusty",
    "focus_areas": "Daily greetings, small talk, and polite terms."
  },
  {
    "id": "PO-B-04",
    "language": "Portuguese",
    "level": "Beginner",
    "phase": 1,
    "title": "Numbers, Days of the Week, and Calendar",
    "url": "https://www.youtube.com/watch?v=Asj-sjmE5WE",
    "channel": "PortuguesePod101",
    "focus_areas": "Telling dates, numbers 1-100, and essential calendar words."
  },
  {
    "id": "PO-B-05",
    "language": "Portuguese",
    "level": "Beginner",
    "phase": 1,
    "title": "How to Use 'Ser' vs 'Estar' in Portuguese",
    "url": "https://www.youtube.com/watch?v=sXstbqoiOEk",
    "channel": "Speaking Brazilian",
    "focus_areas": "Choosing the correct 'to be' verb natively."
  },
  {
    "id": "PO-B-06",
    "language": "Portuguese",
    "level": "Beginner",
    "phase": 1,
    "title": "Present Tense of Regular Verbs (-AR, -ER, -IR)",
    "url": "https://www.youtube.com/watch?v=BsMTXxCAUk0",
    "channel": "Hello Rusty",
    "focus_areas": "Conjugating standard active verbs in the present tense."
  },
  {
    "id": "PO-B-07",
    "language": "Portuguese",
    "level": "Beginner",
    "phase": 1,
    "title": "Gender of Nouns and Article Agreement",
    "url": "https://www.youtube.com/watch?v=YUnQOtLevD0",
    "channel": "PortuguesePod101",
    "focus_areas": "Masculine and feminine nouns, and singular/plural articles."
  },
  {
    "id": "PO-B-08",
    "language": "Portuguese",
    "level": "Beginner",
    "phase": 1,
    "title": "Possessive Adjectives: Meu, Seu, Nosso",
    "url": "https://www.youtube.com/watch?v=PYSoPTAOWqI",
    "channel": "Speaking Brazilian",
    "focus_areas": "Describing ownership of items and relationships."
  },
  {
    "id": "PO-B-09",
    "language": "Portuguese",
    "level": "Beginner",
    "phase": 1,
    "title": "How to Order Food in Brazil (Comida e Sucos)",
    "url": "https://www.youtube.com/watch?v=FtHtDF-zu6o",
    "channel": "Hello Rusty",
    "focus_areas": "Navigating menus, ordering juices, and paying at restaurants."
  },
  {
    "id": "PO-B-10",
    "language": "Portuguese",
    "level": "Beginner",
    "phase": 1,
    "title": "Essential Directions and Travel Phrases",
    "url": "https://www.youtube.com/watch?v=q6PeaHGMssY",
    "channel": "PortuguesePod101",
    "focus_areas": "Survival phrases for airports, taxis, and city navigation."
  },
  {
    "id": "PO-B-11",
    "language": "Portuguese",
    "level": "Beginner",
    "phase": 2,
    "title": "Reflexive Verbs and Daily Grooming Routine",
    "url": "https://www.youtube.com/watch?v=AJF60-97D-c",
    "channel": "Speaking Brazilian",
    "focus_areas": "Talking about what you do to yourself daily (washing, waking)."
  },
  {
    "id": "PO-B-12",
    "language": "Portuguese",
    "level": "Beginner",
    "phase": 2,
    "title": "Telling Time and Scheduling Events",
    "url": "https://www.youtube.com/watch?v=bcHMafWAOcA",
    "channel": "Hello Rusty",
    "focus_areas": "How to say times, make appointments, and schedule workouts."
  },
  {
    "id": "PO-B-13",
    "language": "Portuguese",
    "level": "Beginner",
    "phase": 2,
    "title": "Brazilian Gym & Anatomy Portuguese",
    "url": "https://www.youtube.com/watch?v=GjqJgqayQ78",
    "channel": "Speaking Brazilian",
    "focus_areas": "Fitness vocabulary specific to muscles, joints, and exercises."
  },
  {
    "id": "PO-B-14",
    "language": "Portuguese",
    "level": "Beginner",
    "phase": 2,
    "title": "Shopping and Bargaining at Brazilian Markets",
    "url": "https://www.youtube.com/watch?v=ylav9uHbGcg",
    "channel": "Hello Rusty",
    "focus_areas": "Grocery list vocabulary and negotiating prices."
  },
  {
    "id": "PO-B-15",
    "language": "Portuguese",
    "level": "Beginner",
    "phase": 2,
    "title": "Describing People: Colors, Clothes, and Adjectives",
    "url": "https://www.youtube.com/watch?v=9CVEAS1x9Sc",
    "channel": "PortuguesePod101",
    "focus_areas": "Vocabulary for clothes, physical descriptions, and colors."
  },
  {
    "id": "PO-B-16",
    "language": "Portuguese",
    "level": "Beginner",
    "phase": 2,
    "title": "Weather Expressions and Seasons in Brazil",
    "url": "https://www.youtube.com/watch?v=Y4hVdOnZl1g",
    "channel": "Speaking Brazilian",
    "focus_areas": "Describing the climate and regional weather patterns."
  },
  {
    "id": "PO-B-17",
    "language": "Portuguese",
    "level": "Beginner",
    "phase": 2,
    "title": "The Verb 'Ter' used as 'There Is' (Há)",
    "url": "https://www.youtube.com/watch?v=gNssHeHgijE",
    "channel": "Hello Rusty",
    "focus_areas": "Grammatical patterns of 'ter' in colloquial Brazilian speech."
  },
  {
    "id": "PO-B-18",
    "language": "Portuguese",
    "level": "Beginner",
    "phase": 2,
    "title": "How to Use 'Gostar de' and 'Precisar de'",
    "url": "https://www.youtube.com/watch?v=1LR9BNuRSBs",
    "channel": "PortuguesePod101",
    "focus_areas": "Preposition requirements with these two fundamental verbs."
  },
  {
    "id": "PO-B-19",
    "language": "Portuguese",
    "level": "Beginner",
    "phase": 2,
    "title": "Simple Future Tense with 'Ir + Infinitive'",
    "url": "https://www.youtube.com/watch?v=O8_DJy8vC8T",
    "channel": "Speaking Brazilian",
    "focus_areas": "Speaking about tomorrow or upcoming workouts."
  },
  {
    "id": "PO-B-20",
    "language": "Portuguese",
    "level": "Beginner",
    "phase": 2,
    "title": "Basic Linking Words (E, Mas, Porque, Então)",
    "url": "https://www.youtube.com/watch?v=uMBraw7BWJv",
    "channel": "Hello Rusty",
    "focus_areas": "Connecting phrases to improve baseline conversation flow."
  },
  {
    "id": "PO-I-01",
    "language": "Portuguese",
    "level": "Intermediate",
    "phase": 3,
    "title": "Preterite Tense (Past Tense) of Regular Verbs",
    "url": "https://www.youtube.com/watch?v=4pxD0qeL900",
    "channel": "Speaking Brazilian",
    "focus_areas": "Mastering past actions that are complete."
  },
  {
    "id": "PO-I-02",
    "language": "Portuguese",
    "level": "Intermediate",
    "phase": 3,
    "title": "Imperfect Tense of Regular Verbs (Past Tense)",
    "url": "https://www.youtube.com/watch?v=QviLRRwIfb8",
    "channel": "Hello Rusty",
    "focus_areas": "Describing ongoing or habitual past actions in Brazil."
  },
  {
    "id": "PO-I-03",
    "language": "Portuguese",
    "level": "Intermediate",
    "phase": 3,
    "title": "Preterite vs Imperfect in Portuguese",
    "url": "https://www.youtube.com/watch?v=bTDHCFODwbo",
    "channel": "Speaking Brazilian",
    "focus_areas": "Key rules to choose the correct past tense contextually."
  },
  {
    "id": "PO-I-04",
    "language": "Portuguese",
    "level": "Intermediate",
    "phase": 3,
    "title": "Pronouns: Direct, Indirect, and Colloquial Use",
    "url": "https://www.youtube.com/watch?v=LEovfST_5BU",
    "channel": "PortuguesePod101",
    "focus_areas": "How object pronouns change in casual spoken Brazilian Portuguese."
  },
  {
    "id": "PO-I-05",
    "language": "Portuguese",
    "level": "Intermediate",
    "phase": 3,
    "title": "Present Subjunctive Basics: Doubts & Desires",
    "url": "https://www.youtube.com/watch?v=zmNCIIakAUA",
    "channel": "Speaking Brazilian",
    "focus_areas": "An introductory look at the subjunctive mood in Portuguese."
  },
  {
    "id": "PO-I-06",
    "language": "Portuguese",
    "level": "Intermediate",
    "phase": 3,
    "title": "Future Subjunctive: 'When I Can' (Quando Eu Puder)",
    "url": "https://www.youtube.com/watch?v=CnK3UxOHFY0",
    "channel": "Speaking Brazilian",
    "focus_areas": "A crucial mood unique to Portuguese for potential future events."
  },
  {
    "id": "PO-I-07",
    "language": "Portuguese",
    "level": "Intermediate",
    "phase": 3,
    "title": "The Personal Infinitive: Natively Portuguese",
    "url": "https://www.youtube.com/watch?v=aZb8fVg3Tc0",
    "channel": "Hello Rusty",
    "focus_areas": "Using the infinitive inflected for person and number."
  },
  {
    "id": "PO-I-08",
    "language": "Portuguese",
    "level": "Intermediate",
    "phase": 3,
    "title": "How to Use 'Por' and 'Para' in Brazil",
    "url": "https://www.youtube.com/watch?v=X_LzSVVNpzg",
    "channel": "Speaking Brazilian",
    "focus_areas": "Mastering these prepositions for travel and daily tasks."
  },
  {
    "id": "PO-I-09",
    "language": "Portuguese",
    "level": "Intermediate",
    "phase": 3,
    "title": "Brazilian Slang and Idioms Every Learner Needs",
    "url": "https://www.youtube.com/watch?v=5I4rOU0AuQ8",
    "channel": "Hello Rusty",
    "focus_areas": "High-frequency slang (cara, mano, legal, bacana)."
  },
  {
    "id": "PO-I-10",
    "language": "Portuguese",
    "level": "Intermediate",
    "phase": 3,
    "title": "Reflexive Pronouns & Reciprocal Verbs",
    "url": "https://www.youtube.com/watch?v=z6qjXDNOXVs",
    "channel": "PortuguesePod101",
    "focus_areas": "Verbs like 'se abraçar' or 'se exercitar' in intermediate speech."
  },
  {
    "id": "PO-I-11",
    "language": "Portuguese",
    "level": "Intermediate",
    "phase": 3,
    "title": "Conditional Tense: Forming Future Hypotheticals",
    "url": "https://www.youtube.com/watch?v=mLmoW8RfKoY",
    "channel": "Speaking Brazilian",
    "focus_areas": "Expressing what you 'would do' under certain conditions."
  },
  {
    "id": "PO-I-12",
    "language": "Portuguese",
    "level": "Intermediate",
    "phase": 3,
    "title": "The Gerund in Brazilian Portuguese (-ando, -endo)",
    "url": "https://www.youtube.com/watch?v=ABNNifZyw2f",
    "channel": "Hello Rusty",
    "focus_areas": "Talking about active, ongoing tasks (estou treinando)."
  },
  {
    "id": "PO-I-13",
    "language": "Portuguese",
    "level": "Intermediate",
    "phase": 3,
    "title": "Health, Body, and Medical Portuguese",
    "url": "https://www.youtube.com/watch?v=6LAfc1GSriz",
    "channel": "Speaking Brazilian",
    "focus_areas": "Vocabulary necessary for clinical symptoms and anatomical features."
  },
  {
    "id": "PO-I-14",
    "language": "Portuguese",
    "level": "Intermediate",
    "phase": 3,
    "title": "Expressing Commands & Cues in Portuguese",
    "url": "https://www.youtube.com/watch?v=37IDiwIOVeS",
    "channel": "PortuguesePod101",
    "focus_areas": "Using commands effectively to instruct clients or teammates."
  },
  {
    "id": "PO-I-15",
    "language": "Portuguese",
    "level": "Intermediate",
    "phase": 3,
    "title": "Intermediate Listening Drills: Fast Spoken Brazilian",
    "url": "https://www.youtube.com/watch?v=ujbPXMt01CQ",
    "channel": "Hello Rusty",
    "focus_areas": "Techniques for parsing accelerated conversational Portuguese."
  },
  {
    "id": "PO-A-01",
    "language": "Portuguese",
    "level": "Advanced",
    "phase": 4,
    "title": "Imperfect Subjunctive (Past Subjunctive) Guide",
    "url": "https://www.youtube.com/watch?v=41psUbfExhQ",
    "channel": "Speaking Brazilian",
    "focus_areas": "Forming 'Se eu pudesse...' and past doubts."
  },
  {
    "id": "PO-A-02",
    "language": "Portuguese",
    "level": "Advanced",
    "phase": 4,
    "title": "Advanced Future Subjunctive Scenarios",
    "url": "https://www.youtube.com/watch?v=do0OGCL9_kn",
    "channel": "Speaking Brazilian",
    "focus_areas": "Using the future subjunctive in complex syntax patterns."
  },
  {
    "id": "PO-A-03",
    "language": "Portuguese",
    "level": "Advanced",
    "phase": 4,
    "title": "Combining Subjunctives in Hypothetical Clauses",
    "url": "https://www.youtube.com/watch?v=mUnJga0uX1X",
    "channel": "PortuguesePod101",
    "focus_areas": "Scaffolding compound sentences using past and conditional tenses."
  },
  {
    "id": "PO-A-04",
    "language": "Portuguese",
    "level": "Advanced",
    "phase": 4,
    "title": "Advanced relative Pronouns: Cujo, O Qual, Quem",
    "url": "https://www.youtube.com/watch?v=DwSCMJ_yXju",
    "channel": "Speaking Brazilian",
    "focus_areas": "Polishing grammar for official or complex conversations."
  },
  {
    "id": "PO-A-05",
    "language": "Portuguese",
    "level": "Advanced",
    "phase": 4,
    "title": "Understanding Regional Brazilian Dialects (Carioca, Paulista, Mineiro)",
    "url": "https://www.youtube.com/watch?v=S4riedeA1_1",
    "channel": "Hello Rusty",
    "focus_areas": "Tuning your ear to varying accents and slang across Brazil."
  },
  {
    "id": "PO-A-06",
    "language": "Portuguese",
    "level": "Advanced",
    "phase": 4,
    "title": "Advanced Discourse Transition Phrases for Fluidity",
    "url": "https://www.youtube.com/watch?v=hoM80rIO-wZ",
    "channel": "Speaking Brazilian",
    "focus_areas": "Phrases for expressing arguments, comparisons, and flow."
  },
  {
    "id": "PO-A-07",
    "language": "Portuguese",
    "level": "Advanced",
    "phase": 4,
    "title": "The Passive Voice and Formal Spoken Patterns",
    "url": "https://www.youtube.com/watch?v=6HqrmUSQvH7",
    "channel": "PortuguesePod101",
    "focus_areas": "How to write and speak using formal relative passive structures."
  },
  {
    "id": "PO-A-08",
    "language": "Portuguese",
    "level": "Advanced",
    "phase": 4,
    "title": "Athletic Coaching, Cueing, and Sports Psychology Scripts",
    "url": "https://www.youtube.com/watch?v=P-I49fXeDau",
    "channel": "Speaking Brazilian",
    "focus_areas": "Advanced bilingual coaching commands and affirmations."
  },
  {
    "id": "PO-A-09",
    "language": "Portuguese",
    "level": "Advanced",
    "phase": 4,
    "title": "Advanced Compound Tenses (Ter + Participle)",
    "url": "https://www.youtube.com/watch?v=lvl-QxI6r94",
    "channel": "Hello Rusty",
    "focus_areas": "Saying 'I have been training' (Tenho treinado) correctly."
  },
  {
    "id": "PO-A-10",
    "language": "Portuguese",
    "level": "Advanced",
    "phase": 4,
    "title": "Verb Nuances: Ficar, Tornar-se, Virar",
    "url": "https://www.youtube.com/watch?v=JKTZ9AIXyv0",
    "channel": "Speaking Brazilian",
    "focus_areas": "The subtle differences in verbs indicating changes of state."
  },
  {
    "id": "PO-A-11",
    "language": "Portuguese",
    "level": "Advanced",
    "phase": 4,
    "title": "Rio de Janeiro Slang (Gírias Cariocas) Deep Dive",
    "url": "https://www.youtube.com/watch?v=EgxI6_nnaqs",
    "channel": "Portuguese With Leo",
    "focus_areas": "Comprehensive look at high-leverage Carioca street expressions."
  },
  {
    "id": "PO-A-12",
    "language": "Portuguese",
    "level": "Advanced",
    "phase": 4,
    "title": "Anatomy, Biometrics, and Science Vocab in Portuguese",
    "url": "https://www.youtube.com/watch?v=hvDItP6aW1a",
    "channel": "Speaking Brazilian",
    "focus_areas": "Technical terms for exercise physiology and medical manufacturing."
  },
  {
    "id": "PO-A-13",
    "language": "Portuguese",
    "level": "Advanced",
    "phase": 4,
    "title": "Mastering Past Narrations: Imperfect, Preterite, Pluperfect",
    "url": "https://www.youtube.com/watch?v=5tDzI5-UV53",
    "channel": "Hello Rusty",
    "focus_areas": "Expressing layered storylines in past conversations."
  },
  {
    "id": "PO-A-14",
    "language": "Portuguese",
    "level": "Advanced",
    "phase": 4,
    "title": "Double Negatives and Subtle Grammatical Errors",
    "url": "https://www.youtube.com/watch?v=V3VNka_ZTuu",
    "channel": "PortuguesePod101",
    "focus_areas": "Avoiding common linguistic mistakes in high-level speech."
  },
  {
    "id": "PO-A-15",
    "language": "Portuguese",
    "level": "Advanced",
    "phase": 4,
    "title": "Advanced Written Accents & Crase (à)",
    "url": "https://www.youtube.com/watch?v=58q1oYWa0oA",
    "channel": "Speaking Brazilian",
    "focus_areas": "Mastering Portuguese orthography, stress rules, and contraction rules."
  }
]